kafal/__init__.py
kafal/cli.py
kafal/core/__init__.py
kafal/core/builtins.py
kafal/core/host_api.py
kafal/core/interpreter.py
kafal/core/lexer.py
kafal/core/meta_inputs.py
kafal/core/parser.py
kafal/core/parser_blocks.py
kafal/core/parser_viz.py
kafal/core/pipe_expr.py
kafal/core/portfolio_state.py
kafal/core/safe_eval.py
kafal/core/strategy_state.py
kafal/utils/__init__.py
kafal/utils/helpers.py
kafal-1.0.1.dist-info/licenses/LICENSE
kafal-1.0.1.dist-info/METADATA
kafal-1.0.1.dist-info/WHEEL
kafal-1.0.1.dist-info/top_level.txt
kafal-1.0.1.dist-info/RECORD
